{
    "Local Cache": {
        "md4c/0.4.8": {
            "revisions": {
                "9b5da52e0c0b803bb0d1a4b9fdfe10b1": {
                    "timestamp": 1721994276.4847488,
                    "packages": {
                        "ecf01d5d901d9724a4977c8382767c45c5a43468": {
                            "info": {
                                "settings": {
                                    "arch": "armv8",
                                    "build_type": "Debug",
                                    "compiler": "clang",
                                    "compiler.version": "14",
                                    "os": "Linux"
                                },
                                "options": {
                                    "encoding": "utf-8",
                                    "fPIC": "True",
                                    "md2html": "True",
                                    "shared": "False"
                                }
                            }
                        }
                    }
                }
            }
        }
    }
}
